motoko/__init__.py
motoko/bd_study.py
motoko/daemon.py
motoko/task_manager.py
motoko/workflow.py
motoko/scripts/__init__.py
motoko/scripts/clean.py
motoko/scripts/create_studies.py
motoko/scripts/info.py
motoko/scripts/kill.py
motoko/scripts/launcher.py
motoko/scripts/main.py
motoko/scripts/orchestrator.py
motoko-0.1.2.dist-info/METADATA
motoko-0.1.2.dist-info/WHEEL
motoko-0.1.2.dist-info/entry_points.txt
motoko-0.1.2.dist-info/top_level.txt
motoko-0.1.2.dist-info/RECORD
