Metadata-Version: 2.4
Name: motoko
Version: 0.1.2
Summary: Versatile Workflow Manager
Author-email: Guillaume Anciaux <guillaume.anciaux@epfl.ch>, Max Ludwig Hodapp <MaxLudwig.Hodapp@mcl.at>
License: GPL-3.0-or-later
Project-URL: homepage, https://gitlab.com/blackdynamite/motoko
Project-URL: repository, https://gitlab.com/blackdynamite/motoko
Project-URL: documentation, https://gitlab.com/blackdynamite/motoko
Requires-Python: >=3.10
Requires-Dist: ase<4.0.0,>=3.24.0
Requires-Dist: blackdynamite>=1.3.5
